{
  "decisions": [
    {
      "title": "C4 scope narrowed to delivery session path",
      "description": "Implement VPVR read path through existing WS session ops by adding getlast and paginated getrange semantics against RangeStore hot model, without touching writer/schema/bus.",
      "phase": "R",
      "alternatives": [
        "Add new dedicated WS module with broader refactor",
        "Change storage interfaces in this commit"
      ],
      "status": "accepted",
      "id": "dec-1771023521817",
      "decidedAt": "2026-02-13T22:58:41.817Z"
    },
    {
      "title": "M3.C4 committed + gates ok",
      "description": "Commit 1df0373 delivered VPVR WS read path (getlast + paginated getrange) from hot RangeStore path. Ordered gates passed: commit-msg-check, docs-check-full, invariants-check, test-unit, test-workspace, test-workspace-race, test-replay-golden, registry-check, lint.",
      "phase": "V",
      "alternatives": [
        "Delay commit and batch with docs",
        "Split pagination into separate commit"
      ],
      "status": "accepted",
      "id": "dec-1771023681193",
      "decidedAt": "2026-02-13T23:01:21.193Z"
    }
  ]
}
